<!DOCTYPE sqlMap PUBLIC "-//iBATIS.com//DTD SQL Map 2.0//EN" "http://ibatis.apache.org/dtd/sql-map-2.dtd">

<sqlMap namespace="GrossRevenueLW">
     <select id="findAll" parameterClass="java.util.HashMap" resultClass="java.util.HashMap">select  *  from GrossRevenueLW</select>
     <select id="findAllByPartialKey" parameterClass="java.util.HashMap" resultClass="java.util.HashMap">select  *  from GrossRevenueLW</select>
     <insert id="insert" parameterClass="java.util.HashMap">
          insert into GrossRevenueLW(GrossRevenueKey
          <isNotEmpty property="GrossRevenueDesc" prepend=",">GrossRevenueDesc</isNotEmpty>
          <isNotEmpty property="LastUpdateUserID" prepend=",">LastUpdateUserID</isNotEmpty>
          <isNotEmpty property="LastUpdateTimeStamp" prepend=",">LastUpdateTimeStamp</isNotEmpty>
          ) values (#GrossRevenueKey:NUMERIC#
          <isNotEmpty property="GrossRevenueDesc" prepend=",">#GrossRevenueDesc#</isNotEmpty>
          <isNotEmpty property="LastUpdateUserID" prepend=",">#LastUpdateUserID#</isNotEmpty>
          <isNotEmpty property="LastUpdateTimeStamp" prepend=",">#LastUpdateTimeStamp#</isNotEmpty>
          )
     </insert>
     <select id="updateFindByKey" parameterClass="java.util.HashMap" resultClass="java.util.HashMap">select GrossRevenueKey, GrossRevenueDesc, LastUpdateUserID, LastUpdateTimeStamp from GrossRevenueLW where GrossRevenueKey = #GrossRevenueKey#</select>
     <update id="update" parameterClass="java.util.HashMap">
          update GrossRevenueLW set
          <dynamic prepend=" ">
               <isNotEmpty property="GrossRevenueDesc" prepend=",">GrossRevenueDesc = #GrossRevenueDesc#</isNotEmpty>
               <isEmpty property="GrossRevenueDesc" prepend=",">GrossRevenueDesc = null</isEmpty>
               <isNotEmpty property="LastUpdateUserID" prepend=",">LastUpdateUserID = #LastUpdateUserID#</isNotEmpty>
               <isEmpty property="LastUpdateUserID" prepend=",">LastUpdateUserID = null</isEmpty>
               <isNotEmpty property="LastUpdateTimeStamp" prepend=",">LastUpdateTimeStamp = #LastUpdateTimeStamp#</isNotEmpty>
               <isEmpty property="LastUpdateTimeStamp" prepend=",">LastUpdateTimeStamp = null</isEmpty>
          </dynamic>
          where GrossRevenueKey = #GrossRevenueKey#
     </update>
     <delete id="delete" parameterClass="java.util.HashMap">delete from GrossRevenueLW where GrossRevenueKey = #GrossRevenueKey#</delete>
     <delete id="deleteAll" parameterClass="java.util.HashMap">delete from GrossRevenueLW</delete>
     <delete id="deleteAllByPartialKey" parameterClass="java.util.HashMap">delete from GrossRevenueLW</delete>
     <select id="findByKey" parameterClass="java.util.HashMap" resultClass="java.util.HashMap">select GrossRevenueKey, GrossRevenueDesc, LastUpdateUserID, LastUpdateTimeStamp from GrossRevenueLW where GrossRevenueKey = #GrossRevenueKey#</select>
     <select id="search" parameterClass="java.util.HashMap" resultClass="java.util.HashMap">select GrossRevenueKey, GrossRevenueDesc, LastUpdateUserID, LastUpdateTimeStamp from GrossRevenueLW</select>
</sqlMap>

